arabicstopwords/__init__.py
arabicstopwords/arabicstopwords.py
arabicstopwords/stopwords_classified.py
arabicstopwords/stopwords_lexicon.py
arabicstopwords/stopwordsallforms.py
arabicstopwords/stopwordstuple.py
arabicstopwords/stopwordtuple.py
Arabic_Stopwords-0.4.2.dist-info/METADATA
Arabic_Stopwords-0.4.2.dist-info/WHEEL
Arabic_Stopwords-0.4.2.dist-info/top_level.txt
Arabic_Stopwords-0.4.2.dist-info/RECORD
